ppafm/GUIWidgets.py
ppafm/GridUtils.py
ppafm/HighLevel.py
ppafm/PPPlot.py
ppafm/__init__.py
ppafm/atomicUtils.py
ppafm/chemistry.py
ppafm/common.py
ppafm/core.py
ppafm/cpp_utils.py
ppafm/data.py
ppafm/elements.py
ppafm/fieldFFT.py
ppafm/file_dat.py
ppafm/fitSpline.py
ppafm/fitting.py
ppafm/io.py
ppafm/version.py
ppafm/cli/__init__.py
ppafm/cli/conv_rho.py
ppafm/cli/generateDFTD3.py
ppafm/cli/generateElFF.py
ppafm/cli/generateElFF_point_charges.py
ppafm/cli/generateLJFF.py
ppafm/cli/generateTraining_PVE.py
ppafm/cli/plot_results.py
ppafm/cli/relaxed_scan.py
ppafm/cli/gui/ExpShifter.py
ppafm/cli/gui/ExpShifter_2tips.py
ppafm/cli/gui/Viewer.py
ppafm/cli/gui/__init__.py
ppafm/cli/gui/ppafm_gui.py
ppafm/cpp/CG.h
ppafm/cpp/Forces.h
ppafm/cpp/Grid.h
ppafm/cpp/GridUtils.cpp
ppafm/cpp/GridUtils_lib.dll
ppafm/cpp/Makefile
ppafm/cpp/Mat3.h
ppafm/cpp/ProbeParticle.cpp
ppafm/cpp/ProbeParticle_lib.dll
ppafm/cpp/Vec2.h
ppafm/cpp/Vec3.h
ppafm/cpp/VecN.h
ppafm/cpp/__init__.py
ppafm/cpp/fastmath.h
ppafm/cpp/fastmath_light.h
ppafm/cpp/fitSpline.cpp
ppafm/cpp/fitSpline_lib.dll
ppafm/cpp/fitting.cpp
ppafm/cpp/fitting_lib.dll
ppafm/cpp/gonioApprox.h
ppafm/cpp/integerOps.h
ppafm/cpp/macroUtils.h
ppafm/cpp/quaternion.h
ppafm/cpp/spline_hermite.h
ppafm/defaults/__init__.py
ppafm/defaults/atomtypes.ini
ppafm/defaults/d3.py
ppafm/defaults/d3_R0.npy
ppafm/defaults/d3_c6.npy
ppafm/defaults/params.ini
ppafm/defaults/valelec_dict.py
ppafm/dev/CG.py
ppafm/dev/COvsCO.py
ppafm/dev/FARFF.py
ppafm/dev/GLView.py
ppafm/dev/MMFF.py
ppafm/dev/Multipoles.py
ppafm/dev/PolyCycles.py
ppafm/dev/ReactiveFF.py
ppafm/dev/SimplePot.py
ppafm/dev/__init__.py
ppafm/dev/atomfit.py
ppafm/dev/cpp_utils.py
ppafm/ml/AuxMap.py
ppafm/ml/CorrectionLoop.py
ppafm/ml/Corrector.py
ppafm/ml/Generator.py
ppafm/ml/__init__.py
ppafm/ocl/AFMulator.py
ppafm/ocl/__init__.py
ppafm/ocl/field.py
ppafm/ocl/oclUtils.py
ppafm/ocl/relax.py
ppafm/ocl/cl/FF.cl
ppafm/ocl/cl/__init__.py
ppafm/ocl/cl/relax.cl
ppafm/ocl/cl/splines.cl
ppafm-0.3.2.dist-info/METADATA
ppafm-0.3.2.dist-info/WHEEL
ppafm-0.3.2.dist-info/entry_points.txt
ppafm-0.3.2.dist-info/top_level.txt
ppafm-0.3.2.dist-info/RECORD
