Metadata-Version: 2.1
Name: ppafm
Version: 0.3.2
Summary: Classical force field model for simulating atomic force microscopy images.
Project-URL: Homepage, https://github.com/Probe-Particle/ProbeParticleModel
Classifier: Development Status :: 3 - Alpha
Classifier: Intended Audience :: Science/Research
Classifier: Natural Language :: English
Classifier: License :: OSI Approved :: MIT License
Classifier: Programming Language :: Python :: 3
Requires-Python: >=3.7
Requires-Dist: matplotlib
Requires-Dist: numpy
Provides-Extra: opencl
Requires-Dist: pyopencl; extra == "opencl"
Requires-Dist: reikna; extra == "opencl"
Requires-Dist: ase; extra == "opencl"
Requires-Dist: PyQt5; platform_system == "Windows" and extra == "opencl"
Provides-Extra: dev
Requires-Dist: bumpver==2023.1124; extra == "dev"
Requires-Dist: pre-commit; extra == "dev"
Requires-Dist: pytest; extra == "dev"
Requires-Dist: pytest-cov; extra == "dev"
Requires-Dist: sphinx; extra == "dev"
Requires-Dist: furo; extra == "dev"
Requires-Dist: myst-parser; extra == "dev"
